wui/__init__.py
wui/wui.py
wsx-1.0.2.dist-info/LICENSE.txt
wsx-1.0.2.dist-info/METADATA
wsx-1.0.2.dist-info/WHEEL
wsx-1.0.2.dist-info/top_level.txt
wsx-1.0.2.dist-info/RECORD
