Metadata-Version: 2.1
Name: wsx
Version: 1.0.2
Summary: my libs
Home-page: https://github.com/shangxianw/wsxlibs2
Author: ShangXian Wang
Author-email: 997049907@qq.om
License: UNKNOWN
Platform: UNKNOWN
Classifier: Programming Language :: Python :: 3
Classifier: License :: OSI Approved :: MIT License
Classifier: Operating System :: OS Independent
Requires-Python: >=3.6
